{
  "header": "Experience",
  "slug": "experience",
  "list": [
    {
      "company": {
        "name": "NYONair",
        "info": "NYONair is aerial/helicopter service company focusing on aerial photography experiences."
      },

      "roles": [
        {
          "position": "Web Developer",
          "start_date": "May 2017",
          "end_date": "Present",
          "achievements": []
        }
      ]
    },
    {
      "company": {
        "name": "ShopKeep",
        "info": "ShopKeep is a software development company working on a point of sale application for iOS devices that’s being used by over 20,000 small businesses."
      },

      "roles": [
        {
          "position": "Front-End Developer",
          "start_date": "March 2016",
          "end_date": "May 2017",
          "achievements": [
            "I’m the lead developer for ShopKeep’s marketing site, <a href='http://www.shopkeep.com' target='_blank'>www.shopkeep.com</a>.",

            "I also manage and maintain their ecommerce site, <a href='http://shop.shopkeep.com' target='_blank'>shop.shopkeep.com</a>.",

            "I developed the front-end of their gift card micro-site, <a href='http://ecardsystems.com/shopkeep' target='_blank'>www.ecardsystems.com/shopkeep</a>.",

            "I developed the front-end of their lead capture micro-site, <a href='http://www.possoftwareguide.com/find-your-pos' target='_blank'>www.possoftwareguide.com/find-your-pos</a>."
          ]
        },
        {
          "position": "Junior Developer/Designer",
          "start_date": "March 2015",
          "end_date": "March 2016",
          "achievements": [
            "I designed and developed landing pages.",

            "I designed google ad banners.",

            "I developed the new blog, <a href='http://www.shopkeep.com/blog' target='_blank'>http://www.shopkeep.com/blog</a>."
          ]
        }
      ]
    },
    {
      "company": {
        "name": "Magnet Media",
        "info": "Magnet Media Films is a content marketing solutions industry leader who created stunning videos for clients such as Google, Microsoft and Good Technology."
      },

      "roles": [
        {
          "position": "Design Intern",
          "start_date": "June 2014",
          "end_date": "March 2015",
          "achievements": [
            "I assisted the Art Director with Magnet Media’s personal branding as well as client projects.",

            "I created visual assets for presentations and other marketing materials.",

            "I redesigned and developed their marketing website."
          ]
        }
      ]
    },
    {
      "company": {
        "name": "Sign Facility",
        "info": "Sign Facility is a printing and signage company in downtown Jersey City with clients including Carlo’s Bakery, Mack Cali and John Hancock."
      },

      "roles": [
        {
          "position": "Designer",
          "start_date": "Oct 2013",
          "end_date": "May 2014",
          "achievements": [
            "I was responsible for the design, prepress, production and production of the prints.",

            "I also handled the digital press printers, laser cutter, vinyl cutter, and the flatbed printer for oversized printing.",

            "I created personalized client print templates using HTML and CSS with a content management system called Online Printing Solutions owned by Electronics For Imaging."
          ]
        }
      ]
    }
  ]
}
